src/__init__.py
src/cli.py
src/git_searcher.py
src/snyk_parser.py
src/swagger_classifier.py
swagger_ui_detector-1.0.0.dist-info/LICENSE.txt
swagger_ui_detector-1.0.0.dist-info/METADATA
swagger_ui_detector-1.0.0.dist-info/WHEEL
swagger_ui_detector-1.0.0.dist-info/entry_points.txt
swagger_ui_detector-1.0.0.dist-info/top_level.txt
swagger_ui_detector-1.0.0.dist-info/RECORD
