Metadata-Version: 2.1
Name: swagger-ui-detector
Version: 1.0.0
Summary: Detecting versions of multiple swagger-uis
Home-page: https://github.com/ArcHound/swagger-ui-detector
Author: Miloslav Homer
Author-email: miloslav.homer@gmail.com
Project-URL: Bug Tracker, https://github.com/ArcHound/swagger-ui-detector/issues
Classifier: Programming Language :: Python :: 3
Classifier: Operating System :: OS Independent
Requires-Python: >=3.8
License-File: LICENSE.txt
Requires-Dist: beautifulsoup4
Requires-Dist: GitPython (>=3.0.8)
Requires-Dist: requests
Requires-Dist: packaging
Requires-Dist: urllib3
Requires-Dist: Click
Requires-Dist: importlib-metadata ; python_version < "3.8"
